{
    "durations": [30, 60, 180, 365],

    "plans": [
        {
            "code": "p1",
            "devices": 1,
            "title": "1 устройство",
            "prices": {
                "RUB": {
                    "30": 299,
                    "60": 550,
                    "180": 1490,
                    "365": 2590
                },
                "USD": {
                    "30": 2.99,
                    "60": 5.5,
                    "180": 14.9,
                    "365": 25.9
                },
                "XTR": {
                    "30": 301,
                    "60": 553,
                    "180": 1496,
                    "365": 2601
                }
            }
        },
        {
            "code": "p3",
            "devices": 3,
            "title": "3 устройства",
            "prices": {
                "RUB": {
                    "30": 349,
                    "60": 642,
                    "180": 1739,
                    "365": 3023
                },
                "USD": {
                    "30": 3.49,
                    "60": 6.42,
                    "180": 17.39,
                    "365": 30.23
                },
                "XTR": {
                    "30": 351,
                    "60": 646,
                    "180": 1746,
                    "365": 3036
                }
            }
        },
        {
            "code": "p3a",
            "devices": 3,
            "title": "3 устройства + доп. профиль",
            "is_public": false,
            "includes_additional_profile": true,
            "upgrade_from": "p3",
            "prices": {
                "RUB": {
                    "30": 498,
                    "60": 940,
                    "180": 2633,
                    "365": 4836
                },
                "USD": {
                    "30": 4.98,
                    "60": 9.4,
                    "180": 26.33,
                    "365": 48.36
                },
                "XTR": {
                    "30": 501,
                    "60": 946,
                    "180": 2644,
                    "365": 4857
                }
            }
        },
        {
            "code": "p5",
            "devices": 5,
            "title": "5 устройств",
            "prices": {
                "RUB": {
                    "30": 449,
                    "60": 826,
                    "180": 2237,
                    "365": 3889
                },
                "USD": {
                    "30": 4.49,
                    "60": 8.26,
                    "180": 22.37,
                    "365": 38.89
                },
                "XTR": {
                    "30": 452,
                    "60": 831,
                    "180": 2246,
                    "365": 3906
                }
            }
        },
        {
            "code": "p5a",
            "devices": 5,
            "title": "5 устройств + доп. профиль",
            "is_public": false,
            "includes_additional_profile": true,
            "upgrade_from": "p5",
            "prices": {
                "RUB": {
                    "30": 598,
                    "60": 1124,
                    "180": 3131,
                    "365": 5702
                },
                "USD": {
                    "30": 5.98,
                    "60": 11.24,
                    "180": 31.31,
                    "365": 57.02
                },
                "XTR": {
                    "30": 602,
                    "60": 1131,
                    "180": 3144,
                    "365": 5727
                }
            }
        }
    ]
}
